datasette_gunicorn/__init__.py
datasette_gunicorn-0.1.1.dist-info/LICENSE
datasette_gunicorn-0.1.1.dist-info/METADATA
datasette_gunicorn-0.1.1.dist-info/WHEEL
datasette_gunicorn-0.1.1.dist-info/entry_points.txt
datasette_gunicorn-0.1.1.dist-info/top_level.txt
datasette_gunicorn-0.1.1.dist-info/RECORD
