Metadata-Version: 2.1
Name: datasette-gunicorn
Version: 0.1.1
Summary: Run a Datasette server using Gunicorn
Home-page: https://github.com/simonw/datasette-gunicorn
Author: Simon Willison
License: Apache License, Version 2.0
Project-URL: Issues, https://github.com/simonw/datasette-gunicorn/issues
Project-URL: CI, https://github.com/simonw/datasette-gunicorn/actions
Project-URL: Changelog, https://github.com/simonw/datasette-gunicorn/releases
Classifier: Framework :: Datasette
Classifier: License :: OSI Approved :: Apache Software License
Requires-Python: >=3.7
License-File: LICENSE
Requires-Dist: datasette (>0.63.2)
Requires-Dist: gunicorn
Provides-Extra: test
Requires-Dist: pytest ; extra == 'test'
Requires-Dist: pytest-asyncio ; extra == 'test'
Requires-Dist: cogapp ; extra == 'test'
